{"errNo": 0, "errStr": "", "name": "CollectGetBookContentV5", "cache": "9a4ce41f79ef716f:42e1", "time": 1709103664, "data": {"bookName": "\u9ed8\u8ba4\u5b66\u4e60\u672c", "bookId": 71620673, "bookType": 2, "createTime": 0, "amount": 552, "hasMore": 1, "page": 8, "list": [{"collectId": 782438, "sid": "a147119c9884493f8637fc828b87854b", "name": "\u6a21\u68f1\u4e24\u53ef", "pinyin": "m\u00f3 l\u00e9ng li\u01ceng k\u011b", "definition": "\u5f62\u5bb9\u5bf9\u4e00\u4ef6\u4e8b\u60c5\u7684\u4e24\u65b9\u9762\u90fd\u4e0d\u5426\u5b9a\uff0c\u6ca1\u6709\u660e\u786e\u7684\u6001\u5ea6\u6216\u4e3b\u5f20\u3002\uff3b\u8fd1\uff3d\u542b\u7cca\u5176\u8bcd\u3002\uff3b\u53cd\uff3d\u65a9\u9489\u622a\u94c1\u3002", "type": "idiom", "delflag": 0, "createTime": 1705825352, "sugPy": "m", "router": "baidudict://com.baidu.dict?page=term&params=%7B%22term%22%3A%22%E6%A8%A1%E6%A3%B1%E4%B8%A4%E5%8F%AF%22%7D", "author": "", "dynasty": "", "body": "", "collectCount": 0, "likeCount": 0, "_id": "", "_type": "VocabItem"}, {"collectId": 782437, "sid": "539b96c6ff864fe59e695f6221713446", "name": "\u8398\u8398", "pinyin": "sh\u0113n sh\u0113n", "definition": "\u4f17\u591a\u7684\u6837\u5b50\u3002", "type": "term", "delflag": 0, "createTime": 1705825333, "sugPy": "s", "router": "baidudict://com.baidu.dict?page=term&params=%7B%22term%22%3A%22%E8%8E%98%E8%8E%98%22%7D", "author": "", "dynasty": "", "body": "", "collectCount": 0, "likeCount": 0, "_id": "", "_type": "VocabItem"}, {"collectId": 782436, "sid": "800652af23ce47afb5b5e7afa7d6638e", "name": "\u8352\u8bde\u4e0d\u7ecf", "pinyin": "hu\u0101ng d\u00e0n b\u00f9 j\u012bng", "definition": "\u8352\u8bde\uff1a\u8352\u5510\u79bb\u5947\u3002\u4e0d\u7ecf\uff1a\u4e0d\u5408\u5e38\u7406\u3002\u975e\u5e38\u8352\u8c2c\uff0c\u4e0d\u5408\u60c5\u7406\u3002", "type": "idiom", "delflag": 0, "createTime": 1705825309, "sugPy": "h", "router": "baidudict://com.baidu.dict?page=term&params=%7B%22term%22%3A%22%E8%8D%92%E8%AF%9E%E4%B8%8D%E7%BB%8F%22%7D", "author": "", "dynasty": "", "body": "", "collectCount": 0, "likeCount": 0, "_id": "", "_type": "VocabItem"}, {"collectId": 781933, "sid": "9376e38696594709a396ad373ff6f3f7", "name": "\u58f0\u8272\u72ac\u9a6c", "pinyin": "sh\u0113ng s\u00e8 qu\u01cen m\u01ce", "definition": "\u58f0\u8272\uff1a\u6b4c\u821e\u548c\u5973\u8272\u3002\u72ac\u9a6c\uff1a\u517b\u72d7\u548c\u9a91\u9a6c\u3002\u6307\u7eb5\u60c5\u4eab\u4e50\u7684\u8150\u673d\u751f\u6d3b\u65b9\u5f0f\u3002\u4e5f\u4f5c\u201c\u58f0\u8272\u72d7\u9a6c\u201d\u3002", "type": "idiom", "delflag": 0, "createTime": 1705653121, "sugPy": "s", "router": "baidudict://com.baidu.dict?page=term&params=%7B%22term%22%3A%22%E5%A3%B0%E8%89%B2%E7%8A%AC%E9%A9%AC%22%7D", "author": "", "dynasty": "", "body": "", "collectCount": 0, "likeCount": 0, "_id": "", "_type": "VocabItem"}, {"collectId": 781928, "sid": "0deeafe88a104b39828a477beed7770c", "name": "\u5206\u5a29", "pinyin": "f\u0113n mi\u01cen", "definition": "\u751f\u5b69\u5b50\u3002", "type": "term", "delflag": 0, "createTime": 1705652346, "sugPy": "f", "router": "baidudict://com.baidu.dict?page=term&params=%7B%22term%22%3A%22%E5%88%86%E5%A8%A9%22%7D", "author": "", "dynasty": "", "body": "", "collectCount": 0, "likeCount": 0, "_id": "", "_type": "VocabItem"}, {"collectId": 781923, "sid": "7532ef74d89c4c08badef46815829a9b", "name": "\u916e", "pinyin": "t\u00f3ng", "definition": "\u6709\u673a\u5316\u5408\u7269\u7684\u4e00\u7c7b\uff0c\u662f\u7fb0\u57fa\u7684\u4e24\u4e2a\u5355\u952e\u5206\u522b\u548c\u4e24\u4e2a\u70c3\u57fa\u8fde\u63a5\u800c\u6210\u7684\u5316\u5408\u7269\u3002[\u82f1ketone]", "type": "word", "delflag": 0, "createTime": 1705649121, "sugPy": "t", "router": "baidudict://com.baidu.dict?page=word&params=%7B%22word%22%3A%22%E9%85%AE%22%7D", "author": "", "dynasty": "", "body": "", "collectCount": 0, "likeCount": 0, "_id": "", "_type": "VocabItem"}, {"collectId": 781914, "sid": "ff5f01b9e178487fa5380d7a16799cb7", "name": "\u9c9c\u4e3a\u4eba\u77e5", "pinyin": "xi\u01cen w\u00e9i r\u00e9n zh\u012b", "definition": "\u9c9c\uff1a\u5c11\u3002\u4e3a\uff1a\u88ab\u3002\u77e5\uff1a\u77e5\u9053\u3002\u5f88\u5c11\u6709\u4eba\u77e5\u9053\u3002", "type": "idiom", "delflag": 0, "createTime": 1705644820, "sugPy": "x", "router": "baidudict://com.baidu.dict?page=term&params=%7B%22term%22%3A%22%E9%B2%9C%E4%B8%BA%E4%BA%BA%E7%9F%A5%22%7D", "author": "", "dynasty": "", "body": "", "collectCount": 0, "likeCount": 0, "_id": "", "_type": "VocabItem"}, {"collectId": 781912, "sid": "f94b231946b04526b17262d112b7fcce", "name": "\u5343\u6c9f\u4e07\u58d1", "pinyin": "qi\u0101n g\u014du w\u00e0n h\u00e8", "definition": "\u5f62\u5bb9\u6c9f\u58d1\u6781\u591a\u3002\u5982\uff1a\u8fdc\u5728\u4eba\u7c7b\u793e\u4f1a\u51fa\u73b0\u4e4b\u524d\u9ec4\u571f\u9ad8\u539f\u65e9\u5df2\u662f\u5343\u6c9f\u4e07\u58d1\u3002", "type": "idiom", "delflag": 0, "createTime": 1705644562, "sugPy": "q", "router": "baidudict://com.baidu.dict?page=term&params=%7B%22term%22%3A%22%E5%8D%83%E6%B2%9F%E4%B8%87%E5%A3%91%22%7D", "author": "", "dynasty": "", "body": "", "collectCount": 0, "likeCount": 0, "_id": "", "_type": "VocabItem"}, {"collectId": 781908, "sid": "9eef7c62c005431d962438e2dc0a84c1", "name": "\u96b6\u5c5e", "pinyin": "l\u00ec sh\u01d4", "definition": "\uff08\u52a8\uff09\uff08\u533a\u57df\u3001\u673a\u6784\u7b49\uff09\u53d7\u7ba1\u8f96\uff1b\u4ece\u5c5e\uff1a\u76f4\u8f96\u5e02\u662f\u76f4\u63a5\uff5e\u56fd\u52a1\u9662\u7684\u57ce\u5e02\u3002\uff3b\u8fd1\uff3d\u9644\u5c5e|\u4ece\u5c5e\u3002", "type": "term", "delflag": 0, "createTime": 1705639674, "sugPy": "l", "router": "baidudict://com.baidu.dict?page=term&params=%7B%22term%22%3A%22%E9%9A%B6%E5%B1%9E%22%7D", "author": "", "dynasty": "", "body": "", "collectCount": 0, "likeCount": 0, "_id": "", "_type": "VocabItem"}, {"collectId": 781907, "sid": "eaa9a983e0994ee3a1763346d87f4efc", "name": "\u5cb7\u6c5f", "pinyin": "m\u00edn ji\u0101ng", "definition": "\u957f\u6c5f\u652f\u6d41\u3002\u4f4d\u4e8e\u56db\u5ddd\u7701\u4e2d\u90e8\u3002\u53d1\u6e90\u4e8e\u5cb7\u5c71\u7f8a\u818a\u5cad\uff0c\u6d41\u7ecf\u56db\u5ddd\u76c6\u5730\u897f\u90e8\uff0c\u5728\u5b9c\u5bbe\u6c47\u5165\u957f\u6c5f\u3002\u957f711\u5343\u7c73\u3002\u6c34\u529b\u8d44\u6e90\u4e30\u5bcc\u3002\u5728\u90fd\u6c5f\u5830\u5e02\u6709\u8457\u540d\u7684\u90fd\u6c5f\u5830\u6c34\u5229\u5de5\u7a0b\u3002\u90fd\u6c5f\u5830\u5e02\u4ee5\u4e0b\u53ef\u901a\u822a\u3002", "type": "term", "delflag": 0, "createTime": 1705639083, "sugPy": "m", "router": "baidudict://com.baidu.dict?page=term&params=%7B%22term%22%3A%22%E5%B2%B7%E6%B1%9F%22%7D", "author": "", "dynasty": "", "body": "", "collectCount": 0, "likeCount": 0, "_id": "", "_type": "VocabItem"}, {"collectId": 781884, "sid": "9016674e5b6e472a84acad030a99cf20", "name": "\u6da7", "pinyin": "ji\u00e0n", "definition": "\u5c71\u95f4\u6d41\u6c34\u7684\u6c9f\uff1a\u6eaa\uff5e\u3002\u5c71\uff5e\u3002", "type": "word", "delflag": 0, "createTime": 1705635754, "sugPy": "j", "router": "baidudict://com.baidu.dict?page=word&params=%7B%22word%22%3A%22%E6%B6%A7%22%7D", "author": "", "dynasty": "", "body": "", "collectCount": 0, "likeCount": 0, "_id": "", "_type": "VocabItem"}, {"collectId": 781883, "sid": "7799398e70a44d27ad7bbcfc0401e370", "name": "\u623e\u6c14", "pinyin": "l\u00ec q\u00ec", "definition": "\u4e56\u623e\u3001\u51f6\u66b4\u4e4b\u6c14\u3002\u5982\uff1a\u300c\u5316\u623e\u6c14\u4e3a\u7965\u548c\u3002\u300d", "type": "term", "delflag": 0, "createTime": 1705635482, "sugPy": "l", "router": "baidudict://com.baidu.dict?page=term&params=%7B%22term%22%3A%22%E6%88%BE%E6%B0%94%22%7D", "author": "", "dynasty": "", "body": "", "collectCount": 0, "likeCount": 0, "_id": "", "_type": "VocabItem"}, {"collectId": 781870, "sid": "16d10f9381e040a58d35634c5e1eadb2", "name": "\u909b", "pinyin": "qi\u00f3ng", "definition": "\u909b\u5d03\uff08Qi\u00f3ngl\u00e1i\uff09\uff0c\u5c71\u540d\uff0c\u5728\u56db\u5ddd\u3002", "type": "word", "delflag": 0, "createTime": 1705631397, "sugPy": "q", "router": "baidudict://com.baidu.dict?page=word&params=%7B%22word%22%3A%22%E9%82%9B%22%7D", "author": "", "dynasty": "", "body": "", "collectCount": 0, "likeCount": 0, "_id": "", "_type": "VocabItem"}, {"collectId": 781869, "sid": "f9cac43465964bd6a2e247d9c860e8cb", "name": "\u4e09\u53c9\u621f", "pinyin": "s\u0101n ch\u0101 j\u01d0", "definition": "\u53e4\u4ee3\u795e\u8bdd\u4e2d\u6d77\u795e\u6240\u6301\u7684\u6709\u4e09\u5c16\u5934\u7684\u77db\u67aa\u6216\u8282\u6756\u3002\u662f\u53e4\u5e0c\u814a\u795e\u8bdd\u4e2d\u6d77\u795e\u6ce2\u585e\u51ac\u7684\u8c61\u5f81\u7269\u548c\u6b66\u5668\uff0c\u4f20\u8bf4\u662f\u4ed6\u7528\u4e09\u53c9\u5288\u5f00\u5927\u5c71\uff0c\u5c06\u5c71\u77f3\u53d8\u6210\u5c9b\u5c7f\u3002\u540c\u65f6\u7f57\u9a6c\u795e\u8bdd\u4e2d\u5bf9\u5e94\u4e8e\u6ce2\u585e\u51ac\u7684\u5c3c\u666e\u987f\u4e5f\u662f\u4ee5\u4e09\u53c9\u4e3a\u8c61\u5f81\u3002", "type": "term", "delflag": 0, "createTime": 1705631302, "sugPy": "s", "router": "baidudict://com.baidu.dict?page=term&params=%7B%22term%22%3A%22%E4%B8%89%E5%8F%89%E6%88%9F%22%7D", "author": "", "dynasty": "", "body": "", "collectCount": 0, "likeCount": 0, "_id": "", "_type": "VocabItem"}, {"collectId": 781803, "sid": "2fccbe49e22d422aabf8081979ece815", "name": "\u5fc3\u733f\u610f\u9a6c", "pinyin": "x\u012bn yu\u00e1n y\u00ec m\u01ce", "definition": "\u5f62\u5bb9\u5fc3\u601d\u4e0d\u5b9a\uff0c\u5ffd\u800c\u60f3\u8fd9\uff0c\u5ffd\u800c\u60f3\u90a3\uff0c\u597d\u50cf\u9a6c\u8dd1\u733f\u8df3\uff0c\u63a7\u5236\u4e0d\u4f4f\u3002\uff3b\u8fd1\uff3d\u4e09\u5fc3\u4e8c\u610f\u3002", "type": "idiom", "delflag": 0, "createTime": 1705576793, "sugPy": "x", "router": "baidudict://com.baidu.dict?page=term&params=%7B%22term%22%3A%22%E5%BF%83%E7%8C%BF%E6%84%8F%E9%A9%AC%22%7D", "author": "", "dynasty": "", "body": "", "collectCount": 0, "likeCount": 0, "_id": "", "_type": "VocabItem"}, {"collectId": 781799, "sid": "1f36139bf335493ca8eaca60c3e72f48", "name": "\u548e\u7531\u81ea\u53d6", "pinyin": "ji\u00f9 y\u00f3u z\u00ec q\u01d4", "definition": "\u906d\u53d7\u60e9\u5904\u3001\u8d23\u5907\u6216\u8005\u5371\u5bb3\u90fd\u662f\u7531\u81ea\u5df1\u9020\u6210\u7684\u3002", "type": "idiom", "delflag": 0, "createTime": 1705574489, "sugPy": "j", "router": "baidudict://com.baidu.dict?page=term&params=%7B%22term%22%3A%22%E5%92%8E%E7%94%B1%E8%87%AA%E5%8F%96%22%7D", "author": "", "dynasty": "", "body": "", "collectCount": 0, "likeCount": 0, "_id": "", "_type": "VocabItem"}, {"collectId": 781794, "sid": "c730ee98fe0b420e8c5197ac84d98c2c", "name": "\u4e50\u5584\u597d\u65bd", "pinyin": "l\u00e8 sh\u00e0n h\u00e0o sh\u012b", "definition": "\uff1a\u559c\u6b22\u3002\u65bd\uff1a\u65bd\u820d\u3002\u4e50\u610f\u505a\u597d\u4e8b\uff0c\u559c\u597d\u65bd\u820d\u3002\u5f62\u5bb9\u4eba\u5fc3\u5730\u5584\u826f\uff0c\u4e50\u4e8e\u52a9\u4eba\u3002\u4e5f\u4f5c\u201c\u597d\u5584\u4e50\u65bd\u201d\u3002", "type": "idiom", "delflag": 0, "createTime": 1705572991, "sugPy": "l", "router": "baidudict://com.baidu.dict?page=term&params=%7B%22term%22%3A%22%E4%B9%90%E5%96%84%E5%A5%BD%E6%96%BD%22%7D", "author": "", "dynasty": "", "body": "", "collectCount": 0, "likeCount": 0, "_id": "", "_type": "VocabItem"}, {"collectId": 781778, "sid": "867b4531b1e843f394a3dc43966a8f3e", "name": "\u9896", "pinyin": "y\u01d0ng", "definition": "\u7a3b\u3001\u9ea6\u7b49\u79be\u8c37\u5b50\u5b9e\u5e26\u8292\u7684\u5916\u58f3\u3002 ", "type": "word", "delflag": 0, "createTime": 1705565485, "sugPy": "y", "router": "baidudict://com.baidu.dict?page=word&params=%7B%22word%22%3A%22%E9%A2%96%22%7D", "author": "", "dynasty": "", "body": "", "collectCount": 0, "likeCount": 0, "_id": "", "_type": "VocabItem"}, {"collectId": 781777, "sid": "4dccd87b9a75161b79531d453e312a88", "name": "\u9e21\u540c\u9e2d\u8bb2", "pinyin": "j\u012b t\u00f3ng y\u0101 ji\u01ceng", "definition": "\u201c\u9e21\u540c\u9e2d\u8bb2\u201d\u5b57\u9762\u610f\u601d\u4e3a\u9e21\u548c\u9e2d\u8bb2\u8bdd\uff0c\u8bed\u8a00\u4e0d\u901a\uff0c\u5f62\u5bb9\u4e24\u4e2a\u4eba\u5e76\u975e\u5171\u540c\u8bed\u8a00\uff0c\u65e0\u6cd5\u6c9f\u901a\uff0c\u4e2d\u6027\u8bcd\u3002", "type": "term", "delflag": 0, "createTime": 1705564855, "sugPy": "j", "router": "baidudict://com.baidu.dict?page=term&params=%7B%22term%22%3A%22%E9%B8%A1%E5%90%8C%E9%B8%AD%E8%AE%B2%22%7D", "author": "", "dynasty": "", "body": "", "collectCount": 0, "likeCount": 0, "_id": "", "_type": "VocabItem"}, {"collectId": 781773, "sid": "d5fc44b0187ea0301864d9d5ceb69a09", "name": "\u4e9f\u5f85", "pinyin": "j\u00ed d\u00e0i", "definition": "\u8feb\u5207\u7b49\u5f85 \u6025\u5207\u9700\u8981\u3002", "type": "term", "delflag": 0, "createTime": 1705563102, "sugPy": "j", "router": "baidudict://com.baidu.dict?page=term&params=%7B%22term%22%3A%22%E4%BA%9F%E5%BE%85%22%7D", "author": "", "dynasty": "", "body": "", "collectCount": 0, "likeCount": 0, "_id": "", "_type": "VocabItem"}, {"collectId": 781770, "sid": "737e4f44dc664aa39dfbcc287b3401a4", "name": "\u98de\u86fe\u6251\u706b", "pinyin": "f\u0113i \u00e9 p\u016b hu\u01d2", "definition": "\u98de\u86fe\u8d74\u706b\u3001\u81ea\u53d6\u706d\u4ea1", "type": "idiom", "delflag": 0, "createTime": 1705560657, "sugPy": "f", "router": "baidudict://com.baidu.dict?page=term&params=%7B%22term%22%3A%22%E9%A3%9E%E8%9B%BE%E6%89%91%E7%81%AB%22%7D", "author": "", "dynasty": "", "body": "", "collectCount": 0, "likeCount": 0, "_id": "", "_type": "VocabItem"}, {"collectId": 781746, "sid": "3d36ec223a124c478821d6931e80e27b", "name": "\u54fa\u4e73", "pinyin": "b\u01d4 r\u01d4", "definition": "\uff08\u52a8\uff09\u5582\u5976\uff1a\uff5e\u671f|\uff5e\u5ba4\u3002", "type": "term", "delflag": 0, "createTime": 1705546831, "sugPy": "b", "router": "baidudict://com.baidu.dict?page=term&params=%7B%22term%22%3A%22%E5%93%BA%E4%B9%B3%22%7D", "author": "", "dynasty": "", "body": "", "collectCount": 0, "likeCount": 0, "_id": "", "_type": "VocabItem"}, {"collectId": 781737, "sid": "fa2d8ed951fb415f87be4be1a22aae75", "name": "\u9f51\u7c89", "pinyin": "j\u012b f\u011bn", "definition": "\u7ec6\u7c89;\u7c89\u672b;\u788e\u5c51\u3002", "type": "term", "delflag": 0, "createTime": 1705539331, "sugPy": "j", "router": "baidudict://com.baidu.dict?page=term&params=%7B%22term%22%3A%22%E9%BD%91%E7%B2%89%22%7D", "author": "", "dynasty": "", "body": "", "collectCount": 0, "likeCount": 0, "_id": "", "_type": "VocabItem"}, {"collectId": 781736, "sid": "ba5912cc86d34bd6be2312f432822458", "name": "\u6740\u4f10", "pinyin": "sh\u0101 f\u00e1", "definition": "\u2236\u6740\u622e\u4e92\u76f8\u6740\u4f10\u3002", "type": "term", "delflag": 0, "createTime": 1705539309, "sugPy": "s", "router": "baidudict://com.baidu.dict?page=term&params=%7B%22term%22%3A%22%E6%9D%80%E4%BC%90%22%7D", "author": "", "dynasty": "", "body": "", "collectCount": 0, "likeCount": 0, "_id": "", "_type": "VocabItem"}, {"collectId": 781685, "sid": "6ad0f1f1e9fb4090925519f046095534", "name": "\u66ae\u972d", "pinyin": "m\u00f9 \u01cei", "definition": "\uff08\u540d\uff09\u592a\u9633\u897f\u843d\u65f6\u7684\u4e91\u96fe\uff1a\uff5e\u6c89\u6c89\u3002", "type": "term", "delflag": 0, "createTime": 1705496191, "sugPy": "m", "router": "baidudict://com.baidu.dict?page=term&params=%7B%22term%22%3A%22%E6%9A%AE%E9%9C%AD%22%7D", "author": "", "dynasty": "", "body": "", "collectCount": 0, "likeCount": 0, "_id": "", "_type": "VocabItem"}, {"collectId": 781683, "sid": "771a779de753435b93c4eff9c37064fa", "name": "\u50ed", "pinyin": "ji\u00e0n", "definition": "\u8d85\u8d8a\u672c\u5206\u3002 \u53e4\u65f6\u6307\u5730\u4f4d\u5728\u4e0b\u7684\u4eba\u5192\u7528\u5730\u4f4d\u5728\u4e0a\u7684\u4eba\u7684\u540d\u4e49\u6216\u793c\u4eea\u3001\u5668\u7269\uff1a\uff5e\u53f7\uff08\u5192\u7528\u5e1d\u738b\u7684\u79f0\u53f7\uff09\u3002\uff5e\u8d8a\uff08\u8d85\u8d8a\u672c\u5206\uff0c\u5192\u7528\u5728\u4e0a\u7684\u4eba\u7684\u540d\u4e49\u6216\u7269\u54c1\uff09\u3002", "type": "word", "delflag": 0, "createTime": 1705496074, "sugPy": "j", "router": "baidudict://com.baidu.dict?page=word&params=%7B%22word%22%3A%22%E5%83%AD%22%7D", "author": "", "dynasty": "", "body": "", "collectCount": 0, "likeCount": 0, "_id": "", "_type": "VocabItem"}, {"collectId": 781681, "sid": "3678fee1883147a0814ea030227425e8", "name": "\u9002\u5f97\u5176\u53cd", "pinyin": "sh\u00ec d\u00e9 q\u00ed f\u01cen", "definition": "\u9002\uff1a\u6070\u5de7\uff0c\u6b63\u597d\u3002\u6070\u6070\u5f97\u5230\u4e0e\u613f\u671b\u76f8\u53cd\u7684\u7ed3\u679c\u3002", "type": "idiom", "delflag": 0, "createTime": 1705495970, "sugPy": "s", "router": "baidudict://com.baidu.dict?page=term&params=%7B%22term%22%3A%22%E9%80%82%E5%BE%97%E5%85%B6%E5%8F%8D%22%7D", "author": "", "dynasty": "", "body": "", "collectCount": 0, "likeCount": 0, "_id": "", "_type": "VocabItem"}, {"collectId": 781674, "sid": "1343e651efbd4369a444416190c8d00b", "name": "\u9e6c", "pinyin": "y\u00f9", "definition": "\u9e1f\uff0c\u4f53\u8272\u6697\u6de1\uff0c\u5634\u7ec6\u957f\uff0c\u817f\u957f\uff0c\u8dbe\u95f4\u6ca1\u6709\u8e7c\u3002\u5e38\u5728\u6d45\u6c34\u8fb9\u6216\u6c34\u7530\u4e2d\u5403\u5c0f\u9c7c\u3001\u8d1d\u7c7b\u3001\u6606\u866b\u7b49\uff0c\u662f\u5019\u9e1f\u3002\u79cd\u7c7b\u8f83\u591a\u3002", "type": "word", "delflag": 0, "createTime": 1705494994, "sugPy": "y", "router": "baidudict://com.baidu.dict?page=word&params=%7B%22word%22%3A%22%E9%B9%AC%22%7D", "author": "", "dynasty": "", "body": "", "collectCount": 0, "likeCount": 0, "_id": "", "_type": "VocabItem"}, {"collectId": 781671, "sid": "72192dcfd925425d8ec119d998aab0b2", "name": "\u81ea\u520e", "pinyin": "z\u00ec w\u011bn", "definition": "\u81ea\u5df1\u5272\u65ad\u8116\u9888;\u81ea\u6740\u3002", "type": "term", "delflag": 0, "createTime": 1705494604, "sugPy": "z", "router": "baidudict://com.baidu.dict?page=term&params=%7B%22term%22%3A%22%E8%87%AA%E5%88%8E%22%7D", "author": "", "dynasty": "", "body": "", "collectCount": 0, "likeCount": 0, "_id": "", "_type": "VocabItem"}, {"collectId": 781655, "sid": "7122b1b922e94dce9206a38ac587bf11", "name": "\u9e31\u9e3a", "pinyin": "ch\u012b xi\u016b", "definition": "\u732b\u5934\u9e70\u4e00\u7c7b\u7684\u9e1f\u3002", "type": "term", "delflag": 0, "createTime": 1705491232, "sugPy": "c", "router": "baidudict://com.baidu.dict?page=term&params=%7B%22term%22%3A%22%E9%B8%B1%E9%B8%BA%22%7D", "author": "", "dynasty": "", "body": "", "collectCount": 0, "likeCount": 0, "_id": "", "_type": "VocabItem"}]}}